{
  "uuid": "d0da1b92-0254-4df1-89af-54338d3c7231",
  "baseRegKey": "11111-22222-33333-44444-5555555",
  "method": "AUTOMATIC",
  "name": "asdf",
  "licenseText": "#\nAuth vers :                     5b\n#\n#       iWorkflow Product License File\n#       DO NOT EDIT THIS FILE!!\n#\n#       Technical Support:\n#       Web                  tech.f5.com\n#       Phone                (206) 272.6888\n#       Fax                  (206) 272.6802\n#       Email (support)      support@f5.com\n#       AskF5                askf5@f5.com\n#                                              #\n#  Only the specific use referenced above is allowed. Any other uses are prohibited.\n#\n#\n#       Warning: Changing the system time while this system is running\n#                with a time-limited license may make the system unusable.\n#\nUsage :                         F5 Internal Product Development\n#\n#\n#  Only the specific use referenced above is allowed. Any other uses are prohibited.\n#\nVendor :                        F5 Networks, Inc.\n#\n#       Module List \n#\nactive module :                 APM, Base, VE GBB (500 CCU)|V93...356|Anti-Virus Checks|Base Endpoint Security Checks|Firewall Checks|Machine Certificate Checks|Network Access|Protected Workspace|Secure Virtual Keyboard|APM, Web Application|App Tunnel|Remote Desktop\nactive module :                 VEP3, Best, 1G, 25 Instances|S71...929|IPV6 Gateway|Rate Shaping|Ram Cache|SDN Services, VE|DENY-VER-V11.4.X|Max Compression, VE|Acceleration Manager, VE|Recycle, BIG-IP, VE|DNS-GTM, Base, 1Gbps|SSL, VE|VEP3, Best, 1G, Add 25 Instances|Routing Bundle, VE|AFM, VE|ASM, VE|DNSSEC|CGN, BIG-IP VE, AFM ONLY|DNS Rate Limit, 1000 QPS|GTM Rate, 1000|PSM, VE\noptional module :               Concurrent Users\noptional module :               Concurrent Users and Access Sessions, VE\noptional module :               VEP3, Best, 1G, Add 4 Instances\n#\n#       Accumulated Tokens for Module\n#       DNS-GTM, Base, 1Gbps  gtm_rate_fallback 1000  key S71...929\n#\n#       Accumulated Tokens for Module\n#       DNS-GTM, Base, 1Gbps  gtm_rate_limit 1000  key S71...929\n#\n#       Accumulated Tokens for Module\n#       DNS-GTM, Base, 1Gbps  ltm_dns_rate_fallback 1000  key S71...929\n#\n#       Accumulated Tokens for Module\n#       DNS-GTM, Base, 1Gbps  ltm_dns_rate_limit 1000  key S71...929\n#\ngtm_rate_fallback :             1000\ngtm_rate_limit :                1000\nltm_dns_rate_fallback :         1000\nltm_dns_rate_limit :            1000\n#\n#       Accumulated Tokens for Modules\n#       VEP3, Best, 1G, 25 Instances      purchased_license_pool_count 25  key S71...929\n#       VEP3, Best, 1G, Add 25 Instances  purchased_license_pool_count 25  key S71...929\n#\npurchased_license_pool_count :  50\n#\n#       Accumulated Tokens for Module\n#       CGN, BIG-IP VE, AFM ONLY  perf_VE_mem_Mb 1  key S71...929\n#\nperf_VE_mem_Mb :                1\n#\n#       Accumulated Tokens for Module\n#       VEP3, Best, 1G, 25 Instances  perf_VE_cores 8  key S71...929\n#\n#       Accumulated Tokens for Module\n#       VEP3, Best, 1G, 25 Instances  perf_VE_throughput_Mbps 1000  key S71...929\n#\nperf_VE_cores :                 8\nperf_VE_throughput_Mbps :       1000\n#\n#       Accumulated Tokens for Module\n#       APM, Base, VE GBB (500 CCU)  apm_access_sessions 2500  key V93...356\n#\n#       Accumulated Tokens for Module\n#       APM, Base, VE GBB (500 CCU)  apm_sessions 500  key V93...356\n#\n#       Accumulated Tokens for Module\n#       APM, Base, VE GBB (500 CCU)  apm_urlf_limited_sessions 2500  key V93...356\n#\napm_access_sessions :           2500\napm_sessions :                  500\napm_urlf_limited_sessions :     2500\n#\n#       License Tokens for Module VEP3, Best, 1G, 25 Instances key S71...929\n#\npurchased_license_pool :        enabled\nmod_ltm :                       enabled\nmod_ilx :                       enabled\nExclusive_Platform :            BIG-IQ Pool\n#\n#       License Tokens for Module SSL, VE key S71...929\n#\nperf_SSL_total_TPS :            UNLIMITED\nperf_SSL_per_core :             enabled\nperf_SSL_Mbps :                 2000\nperf_SSL_cmp :                  enabled\n#\n#       License Tokens for Module APM, Base, VE GBB (500 CCU) key V93...356\n#\nperf_http_compression_Mbps :    UNLIMITED\nperf_compression_per_core :     enabled\nmod_aml :                       enabled\nltm_isession :                  enabled\naam_bandwidth_control :         enabled\n#\n#       License Tokens for Module Routing Bundle, VE key S71...929\n#\nnw_routing_rip :                enabled\nnw_routing_ospf :               enabled\nnw_routing_isis :               enabled\nnw_routing_bgp :                enabled\nnw_routing_bfd :                enabled\n#\n#       License Tokens for Module IPV6 Gateway key S71...929\n#\nnw_ipv6 :                       enabled\n#\n#       License Tokens for Module DNS-GTM, Base, 1Gbps key S71...929\n#\nmod_dnsgtm :                    enabled\nltm_dns_v13 :                   enabled\nltm_dns_lite :                  enabled\nltm_dns_licensed_objects :      UNLIMITED\ngtm_licensed_objects :          UNLIMITED\n#\n#       License Tokens for Module CGN, BIG-IP VE, AFM ONLY key S71...929\n#\nmod_cgnat :                     enabled\nltm_monitor_udp :               enabled\nltm_monitor_tcp_ho :            enabled\nltm_monitor_tcp :               enabled\nltm_monitor_radius :            enabled\nltm_monitor_icmp :              enabled\nltm_monitor_gateway_icmp :      enabled\ndslite :                        enabled\ncgnat :                         enabled\n#\n#       License Tokens for Module ASM, VE key S71...929\n#\nmod_asm :                       enabled\nltm_proxy_content :             enabled\nltm_ha_vlan_failsafe :          enabled\nltm_conn_one_connect_pool :     enabled\n#\n#       License Tokens for Module APM, Base, VE GBB (500 CCU) key V93...356\n#\nmod_apm :                       enabled\napm_pingaccess :                enabled\n#\n#       License Tokens for Module Acceleration Manager, VE key S71...929\n#\nmod_am :                        enabled\n#\n#       License Tokens for Module PSM, VE key S71...929\n#\nmod_afw :                       enabled\n#\n#       License Tokens for Module AFM, VE key S71...929\n#\nmod_afm :                       enabled\nltm_monitor_rule :              enabled\n#\n#       License Tokens for Module Ram Cache key S71...929\n#\nltm_ram_cache :                 enabled\n#\n#       License Tokens for Module SDN Services, VE key S71...929\n#\nltm_network_virtualization :    enabled\n#\n#       License Tokens for Module DNSSEC key S71...929\n#\nltm_dnssec :                    enabled\n#\n#       License Tokens for Module Rate Shaping key S71...929\n#\nltm_bandw_rate_tosque :         enabled\nltm_bandw_rate_fairque :        enabled\nltm_bandw_rate_classl7 :        enabled\nltm_bandw_rate_classl4 :        enabled\nltm_bandw_rate_classes :        enabled\n#\n#       License Tokens for Module Recycle, BIG-IP, VE key S71...929\n#\nlicense_recycle :               enabled\nExclusive_Platform :            Z100\nExclusive_Platform :            Z100H\nExclusive_Platform :            Z100K\nExclusive_Platform :            Z100x\n#\n#       License Tokens for Module DENY-VER-V11.4.X key S71...929\n#\nDeny_version :                  10.*.*\nDeny_version :                  11.0.*\nDeny_version :                  11.1.*\nDeny_version :                  11.2.*\nDeny_version :                  11.3.*\nDeny_version :                  11.4.*\nDeny_version :                  9.*.*\n#\n#       License Tokens for Module APM, Web Application key V93...356\n#\napm_web_applications :          enabled\n#\n#       License Tokens for Module Remote Desktop key V93...356\n#\napm_remote_desktop :            enabled\n#\n#       License Tokens for Module Network Access key V93...356\n#\napm_na :                        enabled\n#\n#       License Tokens for Module Secure Virtual Keyboard key V93...356\n#\napm_ep_svk :                    enabled\n#\n#       License Tokens for Module Protected Workspace key V93...356\n#\napm_ep_pws :                    enabled\n#\n#       License Tokens for Module Machine Certificate Checks key V93...356\n#\napm_ep_machinecert :            enabled\n#\n#       License Tokens for Module Firewall Checks key V93...356\n#\napm_ep_fwcheck :                enabled\n#\n#       License Tokens for Module Anti-Virus Checks key V93...356\n#\napm_ep_avcheck :                enabled\n#\n#       License Tokens for Module Base Endpoint Security Checks key V93...356\n#\napm_ep :                        enabled\n#\n#       License Tokens for Module App Tunnel key V93...356\n#\napm_app_tunnel :                enabled\n#\nlicense_manager_key :           LS0tLS1CRUdJTi...VZLS0tLS0K\n#\n# Debug Msg - Is sol18346625 affected; Usage, \"2017-02-28 00.00.00\", started after requirement date \"2016-04-15 00.00.00\"\n#\n# LC disabled in accordance with https://support.f5.com/kb/en-us/solutions/public/k/18/sol18346625.html\n#\ngtm_lc :                        disabled\n#\n#       Licensing Information \n#\nLicensed date :                 20170310\nLicense start :                 20170309\nLicense end :                   20170410\nService check date :            20170310\n#\n#       Platform Information \n#\nRegistration Key :              11111-22222-33333-44444-5555555\nLicensed version :              2.1.0\nPlatform ID :                   BIG-IQ Pool\n#\n#       Outbound License Dossier Validation\n#\nDossier :                       1aa727...47ba\n#\n#       Outbound License Authorization Signature\n#\nAuthorization :                 31e567c802...80ce1a4\n#\n#-----------------------------------------\n# Copyright 1996-2017, F5 Networks, Inc.\n# All rights reserved. \n#-----------------------------------------\n",
  "isInternal": true,
  "licenseState": {
    "vendor": "F5 Networks, Inc.",
    "licensedDateTime": "2017-03-10T00:00:00-08:00",
    "licensedVersion": "2.1.0",
    "licenseEndDateTime": "2017-04-10T00:00:00-07:00",
    "licenseStartDateTime": "2017-03-09T00:00:00-08:00",
    "registrationKey": "11111-22222-33333-44444-5555555",
    "dossier": "1aa727ff0...302a47ba",
    "authorization": "31e567c8...0ce1a4",
    "usage": "F5 Internal Product Development",
    "platformId": "BIG-IQ Pool",
    "authVers": "5b",
    "serviceCheckDateTime": "2017-03-10T00:00:00-08:00",
    "exclusivePlatform": [
      "BIG-IQ Pool",
      "Z100",
      "Z100H",
      "Z100K",
      "Z100x"
    ],
    "activeModules": [
      "APM, Base, VE GBB (500 CCU)|V93...356|Anti-Virus Checks|Base Endpoint Security Checks|Firewall Checks|Machine Certificate Checks|Network Access|Protected Workspace|Secure Virtual Keyboard|APM, Web Application|App Tunnel|Remote Desktop",
      "VEP3, Best, 1G, 25 Instances|S71...929|IPV6 Gateway|Rate Shaping|Ram Cache|SDN Services, VE|DENY-VER-V11.4.X|Max Compression, VE|Acceleration Manager, VE|Recycle, BIG-IP, VE|DNS-GTM, Base, 1Gbps|SSL, VE|VEP3, Best, 1G, Add 25 Instances|Routing Bundle, VE|AFM, VE|ASM, VE|DNSSEC|CGN, BIG-IP VE, AFM ONLY|DNS Rate Limit, 1000 QPS|GTM Rate, 1000|PSM, VE"
    ],
    "optionalModules": [
      "Concurrent Users",
      "Concurrent Users and Access Sessions, VE",
      "VEP3, Best, 1G, Add 4 Instances"
    ],
    "featureFlags": [
      {
        "featureName": "gtm_rate_fallback",
        "featureValue": "1000"
      },
      {
        "featureName": "gtm_rate_limit",
        "featureValue": "1000"
      },
      {
        "featureName": "ltm_dns_rate_fallback",
        "featureValue": "1000"
      },
      {
        "featureName": "ltm_dns_rate_limit",
        "featureValue": "1000"
      },
      {
        "featureName": "purchased_license_pool_count",
        "featureValue": "50"
      },
      {
        "featureName": "perf_VE_mem_Mb",
        "featureValue": "1"
      },
      {
        "featureName": "perf_VE_cores",
        "featureValue": "8"
      },
      {
        "featureName": "perf_VE_throughput_Mbps",
        "featureValue": "1000"
      },
      {
        "featureName": "apm_access_sessions",
        "featureValue": "2500"
      },
      {
        "featureName": "apm_sessions",
        "featureValue": "500"
      },
      {
        "featureName": "apm_urlf_limited_sessions",
        "featureValue": "2500"
      },
      {
        "featureName": "purchased_license_pool",
        "featureValue": "enabled"
      },
      {
        "featureName": "mod_ltm",
        "featureValue": "enabled"
      },
      {
        "featureName": "mod_ilx",
        "featureValue": "enabled"
      },
      {
        "featureName": "perf_SSL_total_TPS",
        "featureValue": "UNLIMITED"
      },
      {
        "featureName": "perf_SSL_per_core",
        "featureValue": "enabled"
      },
      {
        "featureName": "perf_SSL_Mbps",
        "featureValue": "2000"
      },
      {
        "featureName": "perf_SSL_cmp",
        "featureValue": "enabled"
      },
      {
        "featureName": "perf_http_compression_Mbps",
        "featureValue": "UNLIMITED"
      },
      {
        "featureName": "perf_compression_per_core",
        "featureValue": "enabled"
      },
      {
        "featureName": "mod_aml",
        "featureValue": "enabled"
      },
      {
        "featureName": "ltm_isession",
        "featureValue": "enabled"
      },
      {
        "featureName": "aam_bandwidth_control",
        "featureValue": "enabled"
      },
      {
        "featureName": "nw_routing_rip",
        "featureValue": "enabled"
      },
      {
        "featureName": "nw_routing_ospf",
        "featureValue": "enabled"
      },
      {
        "featureName": "nw_routing_isis",
        "featureValue": "enabled"
      },
      {
        "featureName": "nw_routing_bgp",
        "featureValue": "enabled"
      },
      {
        "featureName": "nw_routing_bfd",
        "featureValue": "enabled"
      },
      {
        "featureName": "nw_ipv6",
        "featureValue": "enabled"
      },
      {
        "featureName": "mod_dnsgtm",
        "featureValue": "enabled"
      },
      {
        "featureName": "ltm_dns_v13",
        "featureValue": "enabled"
      },
      {
        "featureName": "ltm_dns_lite",
        "featureValue": "enabled"
      },
      {
        "featureName": "ltm_dns_licensed_objects",
        "featureValue": "UNLIMITED"
      },
      {
        "featureName": "gtm_licensed_objects",
        "featureValue": "UNLIMITED"
      },
      {
        "featureName": "mod_cgnat",
        "featureValue": "enabled"
      },
      {
        "featureName": "ltm_monitor_udp",
        "featureValue": "enabled"
      },
      {
        "featureName": "ltm_monitor_tcp_ho",
        "featureValue": "enabled"
      },
      {
        "featureName": "ltm_monitor_tcp",
        "featureValue": "enabled"
      },
      {
        "featureName": "ltm_monitor_radius",
        "featureValue": "enabled"
      },
      {
        "featureName": "ltm_monitor_icmp",
        "featureValue": "enabled"
      },
      {
        "featureName": "ltm_monitor_gateway_icmp",
        "featureValue": "enabled"
      },
      {
        "featureName": "dslite",
        "featureValue": "enabled"
      },
      {
        "featureName": "cgnat",
        "featureValue": "enabled"
      },
      {
        "featureName": "mod_asm",
        "featureValue": "enabled"
      },
      {
        "featureName": "ltm_proxy_content",
        "featureValue": "enabled"
      },
      {
        "featureName": "ltm_ha_vlan_failsafe",
        "featureValue": "enabled"
      },
      {
        "featureName": "ltm_conn_one_connect_pool",
        "featureValue": "enabled"
      },
      {
        "featureName": "mod_apm",
        "featureValue": "enabled"
      },
      {
        "featureName": "apm_pingaccess",
        "featureValue": "enabled"
      },
      {
        "featureName": "mod_am",
        "featureValue": "enabled"
      },
      {
        "featureName": "mod_afw",
        "featureValue": "enabled"
      },
      {
        "featureName": "mod_afm",
        "featureValue": "enabled"
      },
      {
        "featureName": "ltm_monitor_rule",
        "featureValue": "enabled"
      },
      {
        "featureName": "ltm_ram_cache",
        "featureValue": "enabled"
      },
      {
        "featureName": "ltm_network_virtualization",
        "featureValue": "enabled"
      },
      {
        "featureName": "ltm_dnssec",
        "featureValue": "enabled"
      },
      {
        "featureName": "ltm_bandw_rate_tosque",
        "featureValue": "enabled"
      },
      {
        "featureName": "ltm_bandw_rate_fairque",
        "featureValue": "enabled"
      },
      {
        "featureName": "ltm_bandw_rate_classl7",
        "featureValue": "enabled"
      },
      {
        "featureName": "ltm_bandw_rate_classl4",
        "featureValue": "enabled"
      },
      {
        "featureName": "ltm_bandw_rate_classes",
        "featureValue": "enabled"
      },
      {
        "featureName": "license_recycle",
        "featureValue": "enabled"
      },
      {
        "featureName": "Deny_version",
        "featureValue": "10.*.*"
      },
      {
        "featureName": "Deny_version",
        "featureValue": "11.0.*"
      },
      {
        "featureName": "Deny_version",
        "featureValue": "11.1.*"
      },
      {
        "featureName": "Deny_version",
        "featureValue": "11.2.*"
      },
      {
        "featureName": "Deny_version",
        "featureValue": "11.3.*"
      },
      {
        "featureName": "Deny_version",
        "featureValue": "11.4.*"
      },
      {
        "featureName": "Deny_version",
        "featureValue": "9.*.*"
      },
      {
        "featureName": "apm_web_applications",
        "featureValue": "enabled"
      },
      {
        "featureName": "apm_remote_desktop",
        "featureValue": "enabled"
      },
      {
        "featureName": "apm_na",
        "featureValue": "enabled"
      },
      {
        "featureName": "apm_ep_svk",
        "featureValue": "enabled"
      },
      {
        "featureName": "apm_ep_pws",
        "featureValue": "enabled"
      },
      {
        "featureName": "apm_ep_machinecert",
        "featureValue": "enabled"
      },
      {
        "featureName": "apm_ep_fwcheck",
        "featureValue": "enabled"
      },
      {
        "featureName": "apm_ep_avcheck",
        "featureValue": "enabled"
      },
      {
        "featureName": "apm_ep",
        "featureValue": "enabled"
      },
      {
        "featureName": "apm_app_tunnel",
        "featureValue": "enabled"
      },
      {
        "featureName": "license_manager_key",
        "featureValue": "LS0tLS1CRUdJTi...S0VZLS0tLS0K"
      },
      {
        "featureName": "gtm_lc",
        "featureValue": "disabled"
      }
    ],
    "generation": 0,
    "lastUpdateMicros": 0
  },
  "totalDeviceLicenses": 50,
  "freeDeviceLicenses": 50,
  "state": "LICENSED",
  "publicKey": [
    48,
    -126,
    1,
    2,
    3,
    1,
    0,
    1
  ],
  "privateKey": "QWqHCYILgiey...3BAwT1lwDuGfs",
  "registeredKey": [
    49,
    -65,
    8,
    -39,
    -123,
    -15,
    33,
    33,
    -9,
    111,
    111,
    -64,
    69,
    -114,
    52,
    78
  ]
}
